[
  {
    "Title": "integer a",
    "Amount": 9441.35,
    "User": {
      "Id": 6
    },
    "Category": {
      "Id": 45
    },
    "Wallet": {
      "Id": 2
    },
    "Date": "7/31/2020"
  },
  {
    "Title": "vulputate elementum",
    "Amount": 2437.16,
    "User": {
      "Id": 9
    },
    "Category": {
      "Id": 16
    },
    "Wallet": {
      "Id": 11
    },
    "Date": "7/10/2020"
  },
  {
    "Title": null,
    "Amount": 3344.93,
    "User": {
      "Id": 10
    },
    "Category": {
      "Id": 34
    },
    "Wallet": {
      "Id": 11
    },
    "Date": "4/19/2021"
  },
  {
    "Title": null,
    "Amount": 6142.38,
    "User": {
      "Id": 7
    },
    "Category": {
      "Id": 50
    },
    "Wallet": {
      "Id": 35
    },
    "Date": "6/19/2021"
  },
  {
    "Title": null,
    "Amount": 4706.13,
    "User": {
      "Id": 6
    },
    "Category": {
      "Id": 25
    },
    "Wallet": {
      "Id": 7
    },
    "Date": "8/27/2020"
  },
  {
    "Title": null,
    "Amount": 1077.82,
    "User": {
      "Id": 7
    },
    "Category": {
      "Id": 50
    },
    "Wallet": {
      "Id": 24
    },
    "Date": "8/4/2020"
  },
  {
    "Title": null,
    "Amount": 4352.46,
    "User": {
      "Id": 3
    },
    "Category": {
      "Id": 46
    },
    "Wallet": {
      "Id": 28
    },
    "Date": "2/6/2021"
  },
  {
    "Title": "rhoncus vestibulum",
    "Amount": 6478.06,
    "User": {
      "Id": 2
    },
    "Category": {
      "Id": 6
    },
    "Wallet": {
      "Id": 22
    },
    "Date": "5/23/2021"
  },
  {
    "Title": "vel dapibus",
    "Amount": 3883.37,
    "User": {
      "Id": 7
    },
    "Category": {
      "Id": 19
    },
    "Wallet": {
      "Id": 18
    },
    "Date": "3/23/2021"
  },
  {
    "Title": null,
    "Amount": 4913.83,
    "User": {
      "Id": 8
    },
    "Category": {
      "Id": 14
    },
    "Wallet": {
      "Id": 14
    },
    "Date": "6/7/2021"
  },
  {
    "Title": null,
    "Amount": 7837.44,
    "User": {
      "Id": 8
    },
    "Category": {
      "Id": 39
    },
    "Wallet": {
      "Id": 26
    },
    "Date": "3/20/2021"
  },
  {
    "Title": "dis parturient",
    "Amount": 9172.12,
    "User": {
      "Id": 2
    },
    "Category": {
      "Id": 1
    },
    "Wallet": {
      "Id": 27
    },
    "Date": "3/31/2020"
  },
  {
    "Title": "justo",
    "Amount": 8228.47,
    "User": {
      "Id": 1
    },
    "Category": {
      "Id": 9
    },
    "Wallet": {
      "Id": 23
    },
    "Date": "3/14/2021"
  },
  {
    "Title": null,
    "Amount": 9986.36,
    "User": {
      "Id": 4
    },
    "Category": {
      "Id": 39
    },
    "Wallet": {
      "Id": 8
    },
    "Date": "5/18/2020"
  },
  {
    "Title": "malesuada in",
    "Amount": 1007.3,
    "User": {
      "Id": 1
    },
    "Category": {
      "Id": 8
    },
    "Wallet": {
      "Id": 27
    },
    "Date": "1/5/2021"
  },
  {
    "Title": "venenatis lacinia",
    "Amount": 2538.7,
    "User": {
      "Id": 2
    },
    "Category": {
      "Id": 15
    },
    "Wallet": {
      "Id": 29
    },
    "Date": "12/11/2020"
  },
  {
    "Title": "ac nulla sed",
    "Amount": 8988.15,
    "User": {
      "Id": 1
    },
    "Category": {
      "Id": 20
    },
    "Wallet": {
      "Id": 20
    },
    "Date": "7/27/2020"
  },
  {
    "Title": null,
    "Amount": 9771.17,
    "User": {
      "Id": 7
    },
    "Category": {
      "Id": 22
    },
    "Wallet": {
      "Id": 26
    },
    "Date": "1/15/2021"
  },
  {
    "Title": "amet lobortis",
    "Amount": 8893.79,
    "User": {
      "Id": 9
    },
    "Category": {
      "Id": 9
    },
    "Wallet": {
      "Id": 30
    },
    "Date": "9/12/2020"
  },
  {
    "Title": null,
    "Amount": 1871.91,
    "User": {
      "Id": 3
    },
    "Category": {
      "Id": 36
    },
    "Wallet": {
      "Id": 3
    },
    "Date": "6/12/2021"
  },
  {
    "Title": "in",
    "Amount": 4523.24,
    "User": {
      "Id": 7
    },
    "Category": {
      "Id": 49
    },
    "Wallet": {
      "Id": 18
    },
    "Date": "8/6/2020"
  },
  {
    "Title": null,
    "Amount": 6135.68,
    "User": {
      "Id": 10
    },
    "Category": {
      "Id": 21
    },
    "Wallet": {
      "Id": 28
    },
    "Date": "7/19/2020"
  },
  {
    "Title": null,
    "Amount": 1951.57,
    "User": {
      "Id": 7
    },
    "Category": {
      "Id": 48
    },
    "Wallet": {
      "Id": 9
    },
    "Date": "5/4/2021"
  },
  {
    "Title": "duis faucibus",
    "Amount": 4081.28,
    "User": {
      "Id": 7
    },
    "Category": {
      "Id": 32
    },
    "Wallet": {
      "Id": 1
    },
    "Date": "3/13/2020"
  },
  {
    "Title": null,
    "Amount": 1502.38,
    "User": {
      "Id": 5
    },
    "Category": {
      "Id": 6
    },
    "Wallet": {
      "Id": 3
    },
    "Date": "3/24/2021"
  },
  {
    "Title": null,
    "Amount": 3303.7,
    "User": {
      "Id": 6
    },
    "Category": {
      "Id": 35
    },
    "Wallet": {
      "Id": 35
    },
    "Date": "5/24/2021"
  },
  {
    "Title": "neque",
    "Amount": 2213.22,
    "User": {
      "Id": 2
    },
    "Category": {
      "Id": 17
    },
    "Wallet": {
      "Id": 12
    },
    "Date": "11/2/2020"
  },
  {
    "Title": "ut",
    "Amount": 5507.32,
    "User": {
      "Id": 4
    },
    "Category": {
      "Id": 46
    },
    "Wallet": {
      "Id": 4
    },
    "Date": "8/31/2020"
  },
  {
    "Title": null,
    "Amount": 3611.51,
    "User": {
      "Id": 2
    },
    "Category": {
      "Id": 41
    },
    "Wallet": {
      "Id": 27
    },
    "Date": "9/6/2020"
  },
  {
    "Title": "sapien placerat",
    "Amount": 2854.36,
    "User": {
      "Id": 8
    },
    "Category": {
      "Id": 37
    },
    "Wallet": {
      "Id": 24
    },
    "Date": "3/13/2021"
  },
  {
    "Title": "mauris",
    "Amount": 3934.04,
    "User": {
      "Id": 10
    },
    "Category": {
      "Id": 28
    },
    "Wallet": {
      "Id": 6
    },
    "Date": "10/5/2020"
  },
  {
    "Title": "sapien",
    "Amount": 3444.86,
    "User": {
      "Id": 3
    },
    "Category": {
      "Id": 33
    },
    "Wallet": {
      "Id": 7
    },
    "Date": "9/2/2020"
  },
  {
    "Title": null,
    "Amount": 9358.74,
    "User": {
      "Id": 9
    },
    "Category": {
      "Id": 33
    },
    "Wallet": {
      "Id": 10
    },
    "Date": "6/18/2021"
  },
  {
    "Title": null,
    "Amount": 4554.11,
    "User": {
      "Id": 9
    },
    "Category": {
      "Id": 32
    },
    "Wallet": {
      "Id": 37
    },
    "Date": "6/28/2021"
  },
  {
    "Title": "ut mauris eget",
    "Amount": 1289.26,
    "User": {
      "Id": 1
    },
    "Category": {
      "Id": 45
    },
    "Wallet": {
      "Id": 19
    },
    "Date": "5/7/2021"
  },
  {
    "Title": "rutrum neque aenean",
    "Amount": 6698.57,
    "User": {
      "Id": 3
    },
    "Category": {
      "Id": 18
    },
    "Wallet": {
      "Id": 16
    },
    "Date": "3/19/2020"
  },
  {
    "Title": null,
    "Amount": 7375.53,
    "User": {
      "Id": 7
    },
    "Category": {
      "Id": 12
    },
    "Wallet": {
      "Id": 12
    },
    "Date": "9/21/2020"
  },
  {
    "Title": null,
    "Amount": 8688.53,
    "User": {
      "Id": 6
    },
    "Category": {
      "Id": 23
    },
    "Wallet": {
      "Id": 2
    },
    "Date": "1/30/2021"
  },
  {
    "Title": "ac neque duis",
    "Amount": 9645.16,
    "User": {
      "Id": 5
    },
    "Category": {
      "Id": 28
    },
    "Wallet": {
      "Id": 19
    },
    "Date": "10/29/2020"
  },
  {
    "Title": "sagittis nam",
    "Amount": 3391.83,
    "User": {
      "Id": 7
    },
    "Category": {
      "Id": 2
    },
    "Wallet": {
      "Id": 15
    },
    "Date": "5/18/2021"
  },
  {
    "Title": null,
    "Amount": 1094.54,
    "User": {
      "Id": 6
    },
    "Category": {
      "Id": 2
    },
    "Wallet": {
      "Id": 39
    },
    "Date": "6/8/2020"
  },
  {
    "Title": "nonummy maecenas",
    "Amount": 3317.92,
    "User": {
      "Id": 1
    },
    "Category": {
      "Id": 20
    },
    "Wallet": {
      "Id": 28
    },
    "Date": "4/23/2020"
  },
  {
    "Title": null,
    "Amount": 5279.92,
    "User": {
      "Id": 9
    },
    "Category": {
      "Id": 15
    },
    "Wallet": {
      "Id": 25
    },
    "Date": "1/6/2021"
  },
  {
    "Title": "velit",
    "Amount": 6209.19,
    "User": {
      "Id": 7
    },
    "Category": {
      "Id": 12
    },
    "Wallet": {
      "Id": 13
    },
    "Date": "11/24/2020"
  },
  {
    "Title": "a feugiat",
    "Amount": 4587.99,
    "User": {
      "Id": 4
    },
    "Category": {
      "Id": 37
    },
    "Wallet": {
      "Id": 32
    },
    "Date": "9/3/2020"
  },
  {
    "Title": "velit nec",
    "Amount": 2467.55,
    "User": {
      "Id": 9
    },
    "Category": {
      "Id": 29
    },
    "Wallet": {
      "Id": 26
    },
    "Date": "5/13/2020"
  },
  {
    "Title": "suscipit",
    "Amount": 8882.58,
    "User": {
      "Id": 5
    },
    "Category": {
      "Id": 39
    },
    "Wallet": {
      "Id": 20
    },
    "Date": "6/7/2020"
  },
  {
    "Title": "purus sit",
    "Amount": 7245.44,
    "User": {
      "Id": 4
    },
    "Category": {
      "Id": 36
    },
    "Wallet": {
      "Id": 3
    },
    "Date": "6/12/2020"
  },
  {
    "Title": null,
    "Amount": 4744.16,
    "User": {
      "Id": 10
    },
    "Category": {
      "Id": 27
    },
    "Wallet": {
      "Id": 12
    },
    "Date": "9/26/2020"
  },
  {
    "Title": "interdum mauris non",
    "Amount": 3487.82,
    "User": {
      "Id": 4
    },
    "Category": {
      "Id": 44
    },
    "Wallet": {
      "Id": 6
    },
    "Date": "5/22/2021"
  }
]
